microsoft_agents_a365/notifications/__init__.py
microsoft_agents_a365/notifications/agent_notification.py
microsoft_agents_a365/notifications/models/__init__.py
microsoft_agents_a365/notifications/models/agent_lifecycle_event.py
microsoft_agents_a365/notifications/models/agent_notification_activity.py
microsoft_agents_a365/notifications/models/agent_subchannel.py
microsoft_agents_a365/notifications/models/email_reference.py
microsoft_agents_a365/notifications/models/email_response.py
microsoft_agents_a365/notifications/models/notification_types.py
microsoft_agents_a365/notifications/models/wpx_comment.py
microsoft_agents_a365_notifications-0.2.1.dev9.dist-info/METADATA
microsoft_agents_a365_notifications-0.2.1.dev9.dist-info/WHEEL
microsoft_agents_a365_notifications-0.2.1.dev9.dist-info/top_level.txt
microsoft_agents_a365_notifications-0.2.1.dev9.dist-info/RECORD
